secontrol/__init__.py
secontrol/_version.py
secontrol/admin.py
secontrol/base_device.py
secontrol/common.py
secontrol/device_types.py
secontrol/grids.py
secontrol/inventory.py
secontrol/item_types.py
secontrol/redis_client.py
secontrol/controllers/__init__.py
secontrol/controllers/radar_controller.py
secontrol/controllers/shared_map_controller.py
secontrol/controllers/surface_flight_controller.py
secontrol/devices/__init__.py
secontrol/devices/ai_device.py
secontrol/devices/artillery_device.py
secontrol/devices/assembler_device.py
secontrol/devices/battery_device.py
secontrol/devices/build_and_repair_device.py
secontrol/devices/cockpit_device.py
secontrol/devices/connector_device.py
secontrol/devices/container_device.py
secontrol/devices/conveyor_sorter_device.py
secontrol/devices/display_device.py
secontrol/devices/gas_generator_device.py
secontrol/devices/gyro_device.py
secontrol/devices/lamp_device.py
secontrol/devices/large_turret_device.py
secontrol/devices/nanobot_drill_system_device.py
secontrol/devices/ore_detector_device.py
secontrol/devices/projector_device.py
secontrol/devices/reactor_device.py
secontrol/devices/refinery_device.py
secontrol/devices/remote_control_device.py
secontrol/devices/rover_device.py
secontrol/devices/ship_drill_device.py
secontrol/devices/ship_grinder_device.py
secontrol/devices/ship_tool_device.py
secontrol/devices/ship_welder_device.py
secontrol/devices/thruster_device.py
secontrol/devices/weapon_device.py
secontrol/devices/wheel_device.py
secontrol/tools/__init__.py
secontrol/tools/blueprint_editor.py
secontrol/tools/check_redis_user.py
secontrol/tools/create_restricted_redis_user.py
secontrol/tools/navigation_tools.py
secontrol/tools/radar_navigation.py
secontrol/tools/radar_visualizer.py
secontrol/tools/redis_example_sub.py
secontrol/tools/redis_get_key.py
secontrol/tools/send_chat_message.py
secontrol/tools/telemetry_reader.py
secontrol/tools/telemetry_reader_gui.py
secontrol/tools/update_telemetry_example.py
secontrol-0.3.0.dist-info/licenses/LICENSE
secontrol-0.3.0.dist-info/METADATA
secontrol-0.3.0.dist-info/WHEEL
secontrol-0.3.0.dist-info/top_level.txt
secontrol-0.3.0.dist-info/RECORD
