Metadata-Version: 2.4
Name: secontrol
Version: 0.3.0
Summary: Space Engineers Redis helper utilities
Home-page: https://github.com/rootfabric/secontrol
Author: secontrol contributors
License-Expression: MIT
Project-URL: Homepage, https://www.outenemy.ru/se
Project-URL: Repository, https://github.com/rootfabric/secontrol
Project-URL: Issues, https://github.com/rootfabric/secontrol/issues
Classifier: Development Status :: 3 - Alpha
Classifier: Intended Audience :: Developers
Classifier: Programming Language :: Python
Classifier: Programming Language :: Python :: 3
Classifier: Programming Language :: Python :: 3.9
Classifier: Programming Language :: Python :: 3.10
Classifier: Programming Language :: Python :: 3.11
Classifier: Programming Language :: Python :: 3.12
Classifier: Topic :: Software Development :: Libraries :: Python Modules
Classifier: Topic :: Utilities
Requires-Python: >=3.9
License-File: LICENSE
Requires-Dist: redis>=4.5
Requires-Dist: python-dotenv>=1.0
Requires-Dist: numpy>=1.26
Provides-Extra: dev
Requires-Dist: pytest>=7; extra == "dev"
Requires-Dist: build>=1.2; extra == "dev"
Requires-Dist: twine>=4.0; extra == "dev"
Dynamic: home-page
Dynamic: license-file
Dynamic: requires-python
